{
  "last_updated": "2025-11-13T19:18:42.120580+00:00",
  "components": [
    {
      "symbol": "ACEL",
      "price": 10.27,
      "weight": 0.01470588235294118,
      "region": "North America"
    },
    {
      "symbol": "AGI",
      "price": 33.1,
      "weight": 0.01470588235294118,
      "region": "Asia-Pacific"
    },
    {
      "symbol": "ALL",
      "price": 211.67,
      "weight": 0.01470588235294118,
      "region": "Asia-Pacific"
    },
    {
      "symbol": "BALY",
      "price": 16.9,
      "weight": 0.01470588235294118,
      "region": "North America"
    },
    {
      "symbol": "BNJ",
      "price": 15.4299,
      "weight": 0.01470588235294118,
      "region": "Europe"
    },
    {
      "symbol": "BBT",
      "price": 25.35,
      "weight": 0.01470588235294118,
      "region": "Asia-Pacific"
    },
    {
      "symbol": "BRAG.TO",
      "price": 2.4397,
      "weight": 0.01470588235294118,
      "region": "North America"
    },
    {
      "symbol": "BYD",
      "price": 81.1,
      "weight": 0.01470588235294118,
      "region": "North America"
    },
    {
      "symbol": "BRAG",
      "price": 2.4397,
      "weight": 0.01470588235294118,
      "region": "North America"
    },
    {
      "symbol": "CZR",
      "price": 19.655,
      "weight": 0.01470588235294118,
      "region": "North America"
    },
    {
      "symbol": "CTM",
      "price": 1.1602,
      "weight": 0.01470588235294118,
      "region": "Europe"
    },
    {
      "symbol": "CNTY",
      "price": 1.62,
      "weight": 0.01470588235294118,
      "region": "North America"
    },
    {
      "symbol": "CHDN",
      "price": 100.375,
      "weight": 0.01470588235294118,
      "region": "North America"
    },
    {
      "symbol": "CDRO",
      "price": 5.81,
      "weight": 0.01470588235294118,
      "region": "North America"
    },
    {
      "symbol": "PLUS",
      "price": 90.29,
      "weight": 0.01470588235294118,
      "region": "Other"
    },
    {
      "symbol": "DDI",
      "price": 9.065,
      "weight": 0.01470588235294118,
      "region": "North America"
    },
    {
      "symbol": "DKNG",
      "price": 29.78,
      "weight": 0.01470588235294118,
      "region": "North America"
    },
    {
      "symbol": "EVRI",
      "price": 14.24,
      "weight": 0.01470588235294118,
      "region": "North America"
    },
    {
      "symbol": "EVOK",
      "price": 10.69,
      "weight": 0.01470588235294118,
      "region": "Europe"
    },
    {
      "symbol": "EVO",
      "price": 3.17,
      "weight": 0.01470588235294118,
      "region": "Europe"
    },
    {
      "symbol": "FLUT",
      "price": 202.435,
      "weight": 0.01470588235294118,
      "region": "North America"
    },
    {
      "symbol": "FLL",
      "price": 2.425,
      "weight": 0.01470588235294118,
      "region": "North America"
    },
    {
      "symbol": "GAMB",
      "price": 5.035,
      "weight": 0.01470588235294118,
      "region": "North America"
    },
    {
      "symbol": "GCOR",
      "price": 41.685,
      "weight": 0.01470588235294118,
      "region": "Europe"
    },
    {
      "symbol": "GENI",
      "price": 9.92,
      "weight": 0.01470588235294118,
      "region": "North America"
    },
    {
      "symbol": "GENM",
      "price": 10.2969,
      "weight": 0.01470588235294118,
      "region": "Asia-Pacific"
    },
    {
      "symbol": "GMGI",
      "price": 0.9404,
      "weight": 0.01470588235294118,
      "region": "North America"
    },
    {
      "symbol": "LVS",
      "price": 66.2,
      "weight": 0.01470588235294118,
      "region": "North America"
    },
    {
      "symbol": "LNW",
      "price": 86.22,
      "weight": 0.01470588235294118,
      "region": "North America"
    },
    {
      "symbol": "MLCO",
      "price": 8.99,
      "weight": 0.01470588235294118,
      "region": "North America"
    },
    {
      "symbol": "MGM",
      "price": 33.07,
      "weight": 0.01470588235294118,
      "region": "North America"
    },
    {
      "symbol": "MCRI",
      "price": 96.01,
      "weight": 0.01470588235294118,
      "region": "North America"
    },
    {
      "symbol": "PENN",
      "price": 14.805,
      "weight": 0.01470588235294118,
      "region": "North America"
    },
    {
      "symbol": "AGS",
      "price": 12.49,
      "weight": 0.01470588235294118,
      "region": "North America"
    },
    {
      "symbol": "PBL",
      "price": 31.41,
      "weight": 0.01470588235294118,
      "region": "North America"
    },
    {
      "symbol": "PBH",
      "price": 60.345,
      "weight": 0.01470588235294118,
      "region": "Asia-Pacific"
    },
    {
      "symbol": "RRR",
      "price": 59.28,
      "weight": 0.01470588235294118,
      "region": "North America"
    },
    {
      "symbol": "RSI",
      "price": 17.25,
      "weight": 0.01470588235294118,
      "region": "North America"
    },
    {
      "symbol": "SRAD",
      "price": 22.49,
      "weight": 0.01470588235294118,
      "region": "North America"
    },
    {
      "symbol": "SGHC",
      "price": 12.16,
      "weight": 0.01470588235294118,
      "region": "North America"
    },
    {
      "symbol": "WYNN",
      "price": 123.87,
      "weight": 0.01470588235294118,
      "region": "North America"
    }
  ],
  "values": {
    "All": 23.557085294117652,
    "North America": 16.15727647058824,
    "Europe": 1.0608102941176472,
    "Asia-Pacific": 5.011204411764707,
    "Other": 1.3277941176470591
  }
}