{
  "last_updated": "2025-10-27T09:28:40.512609+00:00",
  "components": [
    {
      "symbol": "ACEL",
      "price": 10.48,
      "weight": 0.01470588235294118,
      "region": "North America"
    },
    {
      "symbol": "AGI",
      "price": 31.55,
      "weight": 0.01470588235294118,
      "region": "Asia-Pacific"
    },
    {
      "symbol": "ALL",
      "price": 193.19,
      "weight": 0.01470588235294118,
      "region": "Asia-Pacific"
    },
    {
      "symbol": "BALY",
      "price": 19.11,
      "weight": 0.01470588235294118,
      "region": "North America"
    },
    {
      "symbol": "BNJ",
      "price": 15.84,
      "weight": 0.01470588235294118,
      "region": "Europe"
    },
    {
      "symbol": "BBT",
      "price": 24.55,
      "weight": 0.01470588235294118,
      "region": "Asia-Pacific"
    },
    {
      "symbol": "BRAG.TO",
      "price": 2.58,
      "weight": 0.01470588235294118,
      "region": "North America"
    },
    {
      "symbol": "BYD",
      "price": 78.77,
      "weight": 0.01470588235294118,
      "region": "North America"
    },
    {
      "symbol": "BRAG",
      "price": 2.58,
      "weight": 0.01470588235294118,
      "region": "North America"
    },
    {
      "symbol": "CZR",
      "price": 22.225,
      "weight": 0.01470588235294118,
      "region": "North America"
    },
    {
      "symbol": "CTM",
      "price": 0.9733,
      "weight": 0.01470588235294118,
      "region": "Europe"
    },
    {
      "symbol": "CNTY",
      "price": 2.23,
      "weight": 0.01470588235294118,
      "region": "North America"
    },
    {
      "symbol": "CHDN",
      "price": 101.0,
      "weight": 0.01470588235294118,
      "region": "North America"
    },
    {
      "symbol": "CDRO",
      "price": 6.56,
      "weight": 0.01470588235294118,
      "region": "North America"
    },
    {
      "symbol": "PLUS",
      "price": 74.39,
      "weight": 0.01470588235294118,
      "region": "Other"
    },
    {
      "symbol": "DDI",
      "price": 8.83,
      "weight": 0.01470588235294118,
      "region": "North America"
    },
    {
      "symbol": "DKNG",
      "price": 33.0,
      "weight": 0.01470588235294118,
      "region": "North America"
    },
    {
      "symbol": "EVRI",
      "price": 14.24,
      "weight": 0.01470588235294118,
      "region": "North America"
    },
    {
      "symbol": "EVOK",
      "price": 4.75,
      "weight": 0.01470588235294118,
      "region": "Europe"
    },
    {
      "symbol": "EVO",
      "price": 4.1,
      "weight": 0.01470588235294118,
      "region": "Europe"
    },
    {
      "symbol": "FLUT",
      "price": 243.92,
      "weight": 0.01470588235294118,
      "region": "North America"
    },
    {
      "symbol": "FLL",
      "price": 2.82,
      "weight": 0.01470588235294118,
      "region": "North America"
    },
    {
      "symbol": "GAMB",
      "price": 7.56,
      "weight": 0.01470588235294118,
      "region": "North America"
    },
    {
      "symbol": "GCOR",
      "price": 42.074,
      "weight": 0.01470588235294118,
      "region": "Europe"
    },
    {
      "symbol": "GENI",
      "price": 12.03,
      "weight": 0.01470588235294118,
      "region": "North America"
    },
    {
      "symbol": "GENM",
      "price": 10.3401,
      "weight": 0.01470588235294118,
      "region": "Asia-Pacific"
    },
    {
      "symbol": "GMGI",
      "price": 1.03,
      "weight": 0.01470588235294118,
      "region": "North America"
    },
    {
      "symbol": "LVS",
      "price": 57.6,
      "weight": 0.01470588235294118,
      "region": "North America"
    },
    {
      "symbol": "LNW",
      "price": 75.89,
      "weight": 0.01470588235294118,
      "region": "North America"
    },
    {
      "symbol": "MLCO",
      "price": 8.32,
      "weight": 0.01470588235294118,
      "region": "North America"
    },
    {
      "symbol": "MGM",
      "price": 32.81,
      "weight": 0.01470588235294118,
      "region": "North America"
    },
    {
      "symbol": "MCRI",
      "price": 91.66,
      "weight": 0.01470588235294118,
      "region": "North America"
    },
    {
      "symbol": "PENN",
      "price": 17.72,
      "weight": 0.01470588235294118,
      "region": "North America"
    },
    {
      "symbol": "AGS",
      "price": 12.49,
      "weight": 0.01470588235294118,
      "region": "North America"
    },
    {
      "symbol": "PBL",
      "price": 31.5,
      "weight": 0.01470588235294118,
      "region": "North America"
    },
    {
      "symbol": "PBH",
      "price": 62.23,
      "weight": 0.01470588235294118,
      "region": "Asia-Pacific"
    },
    {
      "symbol": "RRR",
      "price": 59.07,
      "weight": 0.01470588235294118,
      "region": "North America"
    },
    {
      "symbol": "RSI",
      "price": 19.21,
      "weight": 0.01470588235294118,
      "region": "North America"
    },
    {
      "symbol": "SRAD",
      "price": 27.03,
      "weight": 0.01470588235294118,
      "region": "North America"
    },
    {
      "symbol": "SGHC",
      "price": 11.93,
      "weight": 0.01470588235294118,
      "region": "North America"
    },
    {
      "symbol": "WYNN",
      "price": 125.57,
      "weight": 0.01470588235294118,
      "region": "North America"
    }
  ],
  "values": {
    "All": 23.584594117647065,
    "North America": 16.761250000000004,
    "Europe": 0.9961367647058825,
    "Asia-Pacific": 4.733236764705883,
    "Other": 1.0939705882352944
  }
}