{
  "last_updated": "2025-06-23T08:55:28.345042+00:00",
  "components": [
    {
      "symbol": "ACEL",
      "price": 11.28,
      "weight": 0.01470588235294118,
      "region": "North America"
    },
    {
      "symbol": "AGI",
      "price": 26.45,
      "weight": 0.01470588235294118,
      "region": "Asia-Pacific"
    },
    {
      "symbol": "ALL",
      "price": 195.33,
      "weight": 0.01470588235294118,
      "region": "Asia-Pacific"
    },
    {
      "symbol": "BALY",
      "price": 9.9,
      "weight": 0.01470588235294118,
      "region": "North America"
    },
    {
      "symbol": "BNJ",
      "price": 15.13,
      "weight": 0.01470588235294118,
      "region": "Europe"
    },
    {
      "symbol": "BRAG.TO",
      "price": 4.165,
      "weight": 0.01470588235294118,
      "region": "North America"
    },
    {
      "symbol": "BYD",
      "price": 76.41,
      "weight": 0.01470588235294118,
      "region": "North America"
    },
    {
      "symbol": "BRAG",
      "price": 4.165,
      "weight": 0.01470588235294118,
      "region": "North America"
    },
    {
      "symbol": "CZR",
      "price": 28.15,
      "weight": 0.01470588235294118,
      "region": "North America"
    },
    {
      "symbol": "CTM",
      "price": 1.03,
      "weight": 0.01470588235294118,
      "region": "Europe"
    },
    {
      "symbol": "CNTY",
      "price": 2.45,
      "weight": 0.01470588235294118,
      "region": "North America"
    },
    {
      "symbol": "CHDN",
      "price": 97.9,
      "weight": 0.01470588235294118,
      "region": "North America"
    },
    {
      "symbol": "CDRO",
      "price": 7.69,
      "weight": 0.01470588235294118,
      "region": "North America"
    },
    {
      "symbol": "PLUS",
      "price": 71.79,
      "weight": 0.01470588235294118,
      "region": "Other"
    },
    {
      "symbol": "DDI",
      "price": 8.9,
      "weight": 0.01470588235294118,
      "region": "North America"
    },
    {
      "symbol": "DKNG",
      "price": 40.51,
      "weight": 0.01470588235294118,
      "region": "North America"
    },
    {
      "symbol": "EVRI",
      "price": 14.23,
      "weight": 0.01470588235294118,
      "region": "North America"
    },
    {
      "symbol": "EVOK",
      "price": 2.7531,
      "weight": 0.01470588235294118,
      "region": "Europe"
    },
    {
      "symbol": "EVO",
      "price": 3.76,
      "weight": 0.01470588235294118,
      "region": "Europe"
    },
    {
      "symbol": "FLUT",
      "price": 263.75,
      "weight": 0.01470588235294118,
      "region": "North America"
    },
    {
      "symbol": "FLL",
      "price": 3.89,
      "weight": 0.01470588235294118,
      "region": "North America"
    },
    {
      "symbol": "GAMB",
      "price": 11.64,
      "weight": 0.01470588235294118,
      "region": "North America"
    },
    {
      "symbol": "GCOR",
      "price": 40.94,
      "weight": 0.01470588235294118,
      "region": "Europe"
    },
    {
      "symbol": "GENI",
      "price": 9.61,
      "weight": 0.01470588235294118,
      "region": "North America"
    },
    {
      "symbol": "GENM",
      "price": 10.16,
      "weight": 0.01470588235294118,
      "region": "Asia-Pacific"
    },
    {
      "symbol": "GMGI",
      "price": 1.64,
      "weight": 0.01470588235294118,
      "region": "North America"
    },
    {
      "symbol": "IGT",
      "price": 14.99,
      "weight": 0.01470588235294118,
      "region": "North America"
    },
    {
      "symbol": "LVS",
      "price": 41.68,
      "weight": 0.01470588235294118,
      "region": "North America"
    },
    {
      "symbol": "LNW",
      "price": 85.29,
      "weight": 0.01470588235294118,
      "region": "North America"
    },
    {
      "symbol": "MLCO",
      "price": 6.4,
      "weight": 0.01470588235294118,
      "region": "North America"
    },
    {
      "symbol": "MGM",
      "price": 33.77,
      "weight": 0.01470588235294118,
      "region": "North America"
    },
    {
      "symbol": "MCRI",
      "price": 84.89,
      "weight": 0.01470588235294118,
      "region": "North America"
    },
    {
      "symbol": "PENN",
      "price": 17.05,
      "weight": 0.01470588235294118,
      "region": "North America"
    },
    {
      "symbol": "AGS",
      "price": 12.38,
      "weight": 0.01470588235294118,
      "region": "North America"
    },
    {
      "symbol": "PTEC",
      "price": 37.6676,
      "weight": 0.01470588235294118,
      "region": "Europe"
    },
    {
      "symbol": "PBL",
      "price": 28.6182,
      "weight": 0.01470588235294118,
      "region": "North America"
    },
    {
      "symbol": "PBH",
      "price": 83.44,
      "weight": 0.01470588235294118,
      "region": "Asia-Pacific"
    },
    {
      "symbol": "RRR",
      "price": 50.23,
      "weight": 0.01470588235294118,
      "region": "North America"
    },
    {
      "symbol": "RSI",
      "price": 13.84,
      "weight": 0.01470588235294118,
      "region": "North America"
    },
    {
      "symbol": "SRAD",
      "price": 25.4,
      "weight": 0.01470588235294118,
      "region": "North America"
    },
    {
      "symbol": "SGHC",
      "price": 9.68,
      "weight": 0.01470588235294118,
      "region": "North America"
    },
    {
      "symbol": "WYNN",
      "price": 88.49,
      "weight": 0.01470588235294118,
      "region": "North America"
    }
  ],
  "values": {
    "All": 23.49174852941177,
    "North America": 16.308649999999997,
    "Europe": 1.4894220588235298,
    "Asia-Pacific": 4.63794117647059,
    "Other": 1.0557352941176474
  }
}