{
  "last_updated": "2026-02-06T16:51:08.771906+00:00",
  "components": [
    {
      "symbol": "ACEL",
      "price": 11.275,
      "weight": 0.01470588235294118,
      "region": "North America"
    },
    {
      "symbol": "AGI",
      "price": 39.255,
      "weight": 0.01470588235294118,
      "region": "Asia-Pacific"
    },
    {
      "symbol": "ALL",
      "price": 210.44,
      "weight": 0.01470588235294118,
      "region": "Asia-Pacific"
    },
    {
      "symbol": "BALY",
      "price": 14.57,
      "weight": 0.01470588235294118,
      "region": "North America"
    },
    {
      "symbol": "BNJ",
      "price": 15.76,
      "weight": 0.01470588235294118,
      "region": "Europe"
    },
    {
      "symbol": "BBT",
      "price": 31.52,
      "weight": 0.01470588235294118,
      "region": "Asia-Pacific"
    },
    {
      "symbol": "BRAG.TO",
      "price": 1.875,
      "weight": 0.01470588235294118,
      "region": "North America"
    },
    {
      "symbol": "BYD",
      "price": 83.55,
      "weight": 0.01470588235294118,
      "region": "North America"
    },
    {
      "symbol": "BRAG",
      "price": 1.875,
      "weight": 0.01470588235294118,
      "region": "North America"
    },
    {
      "symbol": "CZR",
      "price": 20.91,
      "weight": 0.01470588235294118,
      "region": "North America"
    },
    {
      "symbol": "CTM",
      "price": 0.864,
      "weight": 0.01470588235294118,
      "region": "Europe"
    },
    {
      "symbol": "CNTY",
      "price": 1.558,
      "weight": 0.01470588235294118,
      "region": "North America"
    },
    {
      "symbol": "CHDN",
      "price": 94.105,
      "weight": 0.01470588235294118,
      "region": "North America"
    },
    {
      "symbol": "CDRO",
      "price": 7.93,
      "weight": 0.01470588235294118,
      "region": "North America"
    },
    {
      "symbol": "PLUS",
      "price": 89.1,
      "weight": 0.01470588235294118,
      "region": "Other"
    },
    {
      "symbol": "DDI",
      "price": 8.39,
      "weight": 0.01470588235294118,
      "region": "North America"
    },
    {
      "symbol": "DKNG",
      "price": 27.1697,
      "weight": 0.01470588235294118,
      "region": "North America"
    },
    {
      "symbol": "EVO",
      "price": 3.58,
      "weight": 0.01470588235294118,
      "region": "Europe"
    },
    {
      "symbol": "FLUT",
      "price": 153.31,
      "weight": 0.01470588235294118,
      "region": "North America"
    },
    {
      "symbol": "FLL",
      "price": 2.26,
      "weight": 0.01470588235294118,
      "region": "North America"
    },
    {
      "symbol": "GAMB",
      "price": 4.395,
      "weight": 0.01470588235294118,
      "region": "North America"
    },
    {
      "symbol": "GCOR",
      "price": 41.595,
      "weight": 0.01470588235294118,
      "region": "Europe"
    },
    {
      "symbol": "GENI",
      "price": 6.395,
      "weight": 0.01470588235294118,
      "region": "North America"
    },
    {
      "symbol": "GENM",
      "price": 10.38,
      "weight": 0.01470588235294118,
      "region": "Asia-Pacific"
    },
    {
      "symbol": "GMGI",
      "price": 0.64205,
      "weight": 0.01470588235294118,
      "region": "North America"
    },
    {
      "symbol": "LVS",
      "price": 57.425,
      "weight": 0.01470588235294118,
      "region": "North America"
    },
    {
      "symbol": "MLCO",
      "price": 6.2,
      "weight": 0.01470588235294118,
      "region": "North America"
    },
    {
      "symbol": "MGM",
      "price": 36.94,
      "weight": 0.01470588235294118,
      "region": "North America"
    },
    {
      "symbol": "MCRI",
      "price": 98.21,
      "weight": 0.01470588235294118,
      "region": "North America"
    },
    {
      "symbol": "PENN",
      "price": 13.05,
      "weight": 0.01470588235294118,
      "region": "North America"
    },
    {
      "symbol": "PBL",
      "price": 30.9474,
      "weight": 0.01470588235294118,
      "region": "North America"
    },
    {
      "symbol": "PBH",
      "price": 65.44,
      "weight": 0.01470588235294118,
      "region": "Asia-Pacific"
    },
    {
      "symbol": "RRR",
      "price": 64.05,
      "weight": 0.01470588235294118,
      "region": "North America"
    },
    {
      "symbol": "RSI",
      "price": 17.41,
      "weight": 0.01470588235294118,
      "region": "North America"
    },
    {
      "symbol": "SRAD",
      "price": 17.19,
      "weight": 0.01470588235294118,
      "region": "North America"
    },
    {
      "symbol": "SGHC",
      "price": 9.04,
      "weight": 0.01470588235294118,
      "region": "North America"
    },
    {
      "symbol": "WYNN",
      "price": 116.05,
      "weight": 0.01470588235294118,
      "region": "North America"
    }
  ],
  "values": {
    "All": 20.803766911764708,
    "North America": 13.334149264705882,
    "Europe": 0.908808823529412,
    "Asia-Pacific": 5.250514705882354,
    "Other": 1.310294117647059
  }
}