{
  "last_updated": "2026-02-25T20:39:05.833647+00:00",
  "components": [
    {
      "symbol": "ACEL",
      "price": 10.955,
      "weight": 0.01470588235294118,
      "region": "North America"
    },
    {
      "symbol": "AGI",
      "price": 50.01,
      "weight": 0.01470588235294118,
      "region": "Asia-Pacific"
    },
    {
      "symbol": "ALL",
      "price": 208.505,
      "weight": 0.01470588235294118,
      "region": "Asia-Pacific"
    },
    {
      "symbol": "BALY",
      "price": 13.455,
      "weight": 0.01470588235294118,
      "region": "North America"
    },
    {
      "symbol": "BNJ",
      "price": 15.4527,
      "weight": 0.01470588235294118,
      "region": "Europe"
    },
    {
      "symbol": "BBT",
      "price": 31.125,
      "weight": 0.01470588235294118,
      "region": "Asia-Pacific"
    },
    {
      "symbol": "BRAG.TO",
      "price": 1.72,
      "weight": 0.01470588235294118,
      "region": "North America"
    },
    {
      "symbol": "BYD",
      "price": 84.69,
      "weight": 0.01470588235294118,
      "region": "North America"
    },
    {
      "symbol": "BRAG",
      "price": 1.72,
      "weight": 0.01470588235294118,
      "region": "North America"
    },
    {
      "symbol": "CZR",
      "price": 20.675,
      "weight": 0.01470588235294118,
      "region": "North America"
    },
    {
      "symbol": "CTM",
      "price": 0.9319,
      "weight": 0.01470588235294118,
      "region": "Europe"
    },
    {
      "symbol": "CNTY",
      "price": 1.625,
      "weight": 0.01470588235294118,
      "region": "North America"
    },
    {
      "symbol": "CHDN",
      "price": 96.13,
      "weight": 0.01470588235294118,
      "region": "North America"
    },
    {
      "symbol": "CDRO",
      "price": 8.02,
      "weight": 0.01470588235294118,
      "region": "North America"
    },
    {
      "symbol": "PLUS",
      "price": 77.895,
      "weight": 0.01470588235294118,
      "region": "Other"
    },
    {
      "symbol": "DDI",
      "price": 8.78,
      "weight": 0.01470588235294118,
      "region": "North America"
    },
    {
      "symbol": "DKNG",
      "price": 22.725,
      "weight": 0.01470588235294118,
      "region": "North America"
    },
    {
      "symbol": "EVO",
      "price": 3.4,
      "weight": 0.01470588235294118,
      "region": "Europe"
    },
    {
      "symbol": "FLUT",
      "price": 119.5075,
      "weight": 0.01470588235294118,
      "region": "North America"
    },
    {
      "symbol": "FLL",
      "price": 2.265,
      "weight": 0.01470588235294118,
      "region": "North America"
    },
    {
      "symbol": "GAMB",
      "price": 4.1854,
      "weight": 0.01470588235294118,
      "region": "North America"
    },
    {
      "symbol": "GCOR",
      "price": 42.03,
      "weight": 0.01470588235294118,
      "region": "Europe"
    },
    {
      "symbol": "GENI",
      "price": 5.94,
      "weight": 0.01470588235294118,
      "region": "North America"
    },
    {
      "symbol": "GENM",
      "price": 10.44,
      "weight": 0.01470588235294118,
      "region": "Asia-Pacific"
    },
    {
      "symbol": "GMGI",
      "price": 0.5546,
      "weight": 0.01470588235294118,
      "region": "North America"
    },
    {
      "symbol": "LVS",
      "price": 54.98,
      "weight": 0.01470588235294118,
      "region": "North America"
    },
    {
      "symbol": "MLCO",
      "price": 5.9,
      "weight": 0.01470588235294118,
      "region": "North America"
    },
    {
      "symbol": "MGM",
      "price": 35.35,
      "weight": 0.01470588235294118,
      "region": "North America"
    },
    {
      "symbol": "MCRI",
      "price": 95.43,
      "weight": 0.01470588235294118,
      "region": "North America"
    },
    {
      "symbol": "PENN",
      "price": 12.435,
      "weight": 0.01470588235294118,
      "region": "North America"
    },
    {
      "symbol": "PBL",
      "price": 31.21,
      "weight": 0.01470588235294118,
      "region": "North America"
    },
    {
      "symbol": "PBH",
      "price": 69.05,
      "weight": 0.01470588235294118,
      "region": "Asia-Pacific"
    },
    {
      "symbol": "RRR",
      "price": 61.71,
      "weight": 0.01470588235294118,
      "region": "North America"
    },
    {
      "symbol": "RSI",
      "price": 19.011,
      "weight": 0.01470588235294118,
      "region": "North America"
    },
    {
      "symbol": "SRAD",
      "price": 17.82,
      "weight": 0.01470588235294118,
      "region": "North America"
    },
    {
      "symbol": "SGHC",
      "price": 10.75,
      "weight": 0.01470588235294118,
      "region": "North America"
    },
    {
      "symbol": "WYNN",
      "price": 107.4,
      "weight": 0.01470588235294118,
      "region": "North America"
    }
  ],
  "values": {
    "All": 20.055633823529412,
    "North America": 12.572698529411769,
    "Europe": 0.9090382352941179,
    "Asia-Pacific": 5.428382352941178,
    "Other": 1.1455147058823532
  }
}